[
  {
    "name": "init_crafting_station",
    "inputs": [
      "ctx: Context < InitCraftingStation >",
      "base_material_cost: u64",
      "success_rate: u8"
    ],
    "nodes": [
      {
        "id": 0,
        "label": "Entry"
      },
      {
        "id": 1,
        "label": "let station = & mut ctx . accounts . crafting_station ;"
      },
      {
        "id": 2,
        "label": "station . crafter = ctx . accounts . crafter . key () ;"
      },
      {
        "id": 3,
        "label": "station . material_mint = ctx . accounts . material_mint . key () ;"
      },
      {
        "id": 4,
        "label": "station . base_material_cost = base_material_cost ;"
      },
      {
        "id": 5,
        "label": "station . success_rate = success_rate ;"
      },
      {
        "id": 6,
        "label": "station . total_crafts_attempted = 0 ;"
      },
      {
        "id": 7,
        "label": "station . successful_crafts = 0 ;"
      },
      {
        "id": 8,
        "label": "station . materials_consumed = 0 ;"
      },
      {
        "id": 9,
        "label": "station . station_type = StationType :: Basic ;"
      },
      {
        "id": 10,
        "label": "Ok (())"
      }
    ],
    "edges": [
      {
        "from": 1,
        "to": 1,
        "label": "def: station"
      },
      {
        "from": 1,
        "to": 2,
        "label": "data_dep: station"
      },
      {
        "from": 1,
        "to": 3,
        "label": "data_dep: station"
      },
      {
        "from": 1,
        "to": 4,
        "label": "data_dep: station"
      },
      {
        "from": 1,
        "to": 5,
        "label": "data_dep: station"
      },
      {
        "from": 1,
        "to": 6,
        "label": "data_dep: station"
      },
      {
        "from": 1,
        "to": 7,
        "label": "data_dep: station"
      },
      {
        "from": 1,
        "to": 8,
        "label": "data_dep: station"
      },
      {
        "from": 1,
        "to": 9,
        "label": "data_dep: station"
      }
    ]
  },
  {
    "name": "execute_craft_attempt",
    "inputs": [
      "ctx: Context < ExecuteCraftAttempt >",
      "recipe_type: CraftingRecipe",
      "enhancement_level: u8"
    ],
    "nodes": [
      {
        "id": 11,
        "label": "Entry"
      },
      {
        "id": 12,
        "label": "let station = & mut ctx . accounts . crafting_station ;"
      },
      {
        "id": 13,
        "label": "let random_seed = Clock :: get () ? . unix_timestamp as u64 ;"
      },
      {
        "id": 14,
        "label": "let recipe_multiplier = match recipe_type { CraftingRecipe :: Common => 1 , CraftingRecipe :: Rare => 3 , CraftingRecipe :: Epic => 7 , CraftingRecipe :: Legendary => 15 , } ;"
      },
      {
        "id": 15,
        "label": "let enhancement_multiplier = (enhancement_level as u64) . saturating_add (1) ;"
      },
      {
        "id": 16,
        "label": "let total_material_cost = station . base_material_cost * recipe_multiplier * enhancement_multiplier ;"
      },
      {
        "id": 17,
        "label": "let mut success_chance = station . success_rate ;"
      },
      {
        "id": 18,
        "label": "if station . successful_crafts > 10 && station . station_type == StationType :: Basic { station . station_type = StationType :: Advanced ; success_chance = success_chance . saturating_add (20) ; }"
      },
      {
        "id": 19,
        "label": "station . station_type = StationType :: Advanced ;"
      },
      {
        "id": 20,
        "label": "success_chance = success_chance . saturating_add (20) ;"
      },
      {
        "id": 21,
        "label": "let mut remaining_cost = total_material_cost ;"
      },
      {
        "id": 22,
        "label": "while remaining_cost > 0 { let burn_amount = std :: cmp :: min (remaining_cost , 50_000 * 10u64 . pow (6)) ; burn (ctx . accounts . burn_materials_ctx () , burn_amount ,) ? ; remaining_cost -= burn_amount ; }"
      },
      {
        "id": 23,
        "label": "let burn_amount = std :: cmp :: min (remaining_cost , 50_000 * 10u64 . pow (6)) ;"
      },
      {
        "id": 24,
        "label": "burn (ctx . accounts . burn_materials_ctx () , burn_amount ,) ? ;"
      },
      {
        "id": 25,
        "label": "remaining_cost -= burn_amount ;"
      },
      {
        "id": 26,
        "label": "station . materials_consumed += total_material_cost ;"
      },
      {
        "id": 27,
        "label": "station . total_crafts_attempted += 1 ;"
      },
      {
        "id": 28,
        "label": "let success = (random_seed % 100) < success_chance as u64 ;"
      },
      {
        "id": 29,
        "label": "if success { station . successful_crafts += 1 ; mint_to (ctx . accounts . mint_nft_ctx () , 1 ,) ? ; }"
      },
      {
        "id": 30,
        "label": "station . successful_crafts += 1 ;"
      },
      {
        "id": 31,
        "label": "mint_to (ctx . accounts . mint_nft_ctx () , 1 ,) ? ;"
      },
      {
        "id": 32,
        "label": "Ok (())"
      }
    ],
    "edges": [
      {
        "from": 12,
        "to": 12,
        "label": "def: station"
      },
      {
        "from": 13,
        "to": 13,
        "label": "def: random_seed"
      },
      {
        "from": 14,
        "to": 14,
        "label": "def: recipe_multiplier"
      },
      {
        "from": 15,
        "to": 15,
        "label": "def: enhancement_multiplier"
      },
      {
        "from": 16,
        "to": 16,
        "label": "def: total_material_cost"
      },
      {
        "from": 12,
        "to": 16,
        "label": "data_dep: station"
      },
      {
        "from": 14,
        "to": 16,
        "label": "data_dep: recipe_multiplier"
      },
      {
        "from": 15,
        "to": 16,
        "label": "data_dep: enhancement_multiplier"
      },
      {
        "from": 17,
        "to": 17,
        "label": "def: success_chance"
      },
      {
        "from": 12,
        "to": 17,
        "label": "data_dep: station"
      },
      {
        "from": 12,
        "to": 18,
        "label": "data_dep: station"
      },
      {
        "from": 12,
        "to": 18,
        "label": "data_dep: station"
      },
      {
        "from": 12,
        "to": 18,
        "label": "data_dep: station"
      },
      {
        "from": 17,
        "to": 18,
        "label": "data_dep: success_chance"
      },
      {
        "from": 17,
        "to": 18,
        "label": "data_dep: success_chance"
      },
      {
        "from": 12,
        "to": 19,
        "label": "data_dep: station"
      },
      {
        "from": 17,
        "to": 20,
        "label": "data_dep: success_chance"
      },
      {
        "from": 17,
        "to": 20,
        "label": "data_dep: success_chance"
      },
      {
        "from": 21,
        "to": 21,
        "label": "def: remaining_cost"
      },
      {
        "from": 16,
        "to": 21,
        "label": "data_dep: total_material_cost"
      },
      {
        "from": 21,
        "to": 22,
        "label": "data_dep: remaining_cost"
      },
      {
        "from": 21,
        "to": 22,
        "label": "data_dep: remaining_cost"
      },
      {
        "from": 21,
        "to": 22,
        "label": "data_dep: remaining_cost"
      },
      {
        "from": 23,
        "to": 23,
        "label": "def: burn_amount"
      },
      {
        "from": 21,
        "to": 23,
        "label": "data_dep: remaining_cost"
      },
      {
        "from": 23,
        "to": 24,
        "label": "data_dep: burn_amount"
      },
      {
        "from": 21,
        "to": 25,
        "label": "data_dep: remaining_cost"
      },
      {
        "from": 23,
        "to": 25,
        "label": "data_dep: burn_amount"
      },
      {
        "from": 12,
        "to": 26,
        "label": "data_dep: station"
      },
      {
        "from": 16,
        "to": 26,
        "label": "data_dep: total_material_cost"
      },
      {
        "from": 12,
        "to": 27,
        "label": "data_dep: station"
      },
      {
        "from": 28,
        "to": 28,
        "label": "def: success"
      },
      {
        "from": 13,
        "to": 28,
        "label": "data_dep: random_seed"
      },
      {
        "from": 17,
        "to": 28,
        "label": "data_dep: success_chance"
      },
      {
        "from": 28,
        "to": 29,
        "label": "data_dep: success"
      },
      {
        "from": 12,
        "to": 29,
        "label": "data_dep: station"
      },
      {
        "from": 12,
        "to": 30,
        "label": "data_dep: station"
      }
    ]
  }
]