[
  {
    "name": "init_archive",
    "inputs": [
      "ctx: Context < InitArchive >"
    ],
    "nodes": [
      {
        "id": 0,
        "label": "Entry"
      },
      {
        "id": 1,
        "label": "let a = & mut ctx . accounts . archive ;"
      },
      {
        "id": 2,
        "label": "a . owner = ctx . accounts . curator . key () ;"
      },
      {
        "id": 3,
        "label": "a . rev = 0 ;"
      },
      {
        "id": 4,
        "label": "a . mask = 0 ;"
      },
      {
        "id": 5,
        "label": "Ok (())"
      }
    ],
    "edges": [
      {
        "from": 1,
        "to": 1,
        "label": "def: a"
      },
      {
        "from": 1,
        "to": 2,
        "label": "data_dep: a"
      },
      {
        "from": 1,
        "to": 3,
        "label": "data_dep: a"
      },
      {
        "from": 1,
        "to": 4,
        "label": "data_dep: a"
      }
    ]
  },
  {
    "name": "init_permit",
    "inputs": [
      "ctx: Context < InitPermit >",
      "permit: Permit"
    ],
    "nodes": [
      {
        "id": 6,
        "label": "Entry"
      },
      {
        "id": 7,
        "label": "let p = & mut ctx . accounts . permit ;"
      },
      {
        "id": 8,
        "label": "p . archive = ctx . accounts . archive . key () ;"
      },
      {
        "id": 9,
        "label": "p . permit = permit ;"
      },
      {
        "id": 10,
        "label": "p . power = 0 ;"
      },
      {
        "id": 11,
        "label": "p . memo = [0 ; 7] ;"
      },
      {
        "id": 12,
        "label": "Ok (())"
      }
    ],
    "edges": [
      {
        "from": 7,
        "to": 7,
        "label": "def: p"
      },
      {
        "from": 7,
        "to": 8,
        "label": "data_dep: p"
      },
      {
        "from": 7,
        "to": 9,
        "label": "data_dep: p"
      },
      {
        "from": 7,
        "to": 10,
        "label": "data_dep: p"
      },
      {
        "from": 7,
        "to": 11,
        "label": "data_dep: p"
      }
    ]
  },
  {
    "name": "edit",
    "inputs": [
      "ctx: Context < Edit >",
      "salt: u64"
    ],
    "nodes": [
      {
        "id": 13,
        "label": "Entry"
      },
      {
        "id": 14,
        "label": "let a = & mut ctx . accounts . archive ;"
      },
      {
        "id": 15,
        "label": "let e = & mut ctx . accounts . editor ;"
      },
      {
        "id": 16,
        "label": "let r = & mut ctx . accounts . reviewer ;"
      },
      {
        "id": 17,
        "label": "let l = & mut ctx . accounts . log ;"
      },
      {
        "id": 18,
        "label": "let mut s = salt ^ a . mask as u64 ;"
      },
      {
        "id": 19,
        "label": "for i in 0 .. 7 { s = s . rotate_left (7) ^ 0xC3A5C85C97CB3127u64 ; e . memo [i] = e . memo [i] . saturating_add (((s >> (i * 8)) & 0xFF) as u32) ; }"
      },
      {
        "id": 20,
        "label": "s = s . rotate_left (7) ^ 0xC3A5C85C97CB3127u64 ;"
      },
      {
        "id": 21,
        "label": "e . memo [i] = e . memo [i] . saturating_add (((s >> (i * 8)) & 0xFF) as u32) ;"
      },
      {
        "id": 22,
        "label": "if e . permit == Write { e . power = e . power . saturating_add (((s & 0xFFFF) as u32) + 9) ; a . rev = a . rev . saturating_add (1) ; a . mask = a . mask ^ ((s as u32) & 0xFFFF) ; l . lines = l . lines . saturating_add (1) ; msg ! (\"Write path applied\") ; } else { r . power = r . power . saturating_add ((((s >> 4) & 0x7FFF) as u32) + 4) ; a . rev = a . rev . saturating_add (1) ; a . mask = a . mask . rotate_right (3) ^ ((s as u32) & 0xFFFF) ; l . lines = l . lines . saturating_add (2) ; msg ! (\"Non-write path applied\") ; }"
      },
      {
        "id": 23,
        "label": "e . power = e . power . saturating_add (((s & 0xFFFF) as u32) + 9) ;"
      },
      {
        "id": 24,
        "label": "a . rev = a . rev . saturating_add (1) ;"
      },
      {
        "id": 25,
        "label": "a . mask = a . mask ^ ((s as u32) & 0xFFFF) ;"
      },
      {
        "id": 26,
        "label": "l . lines = l . lines . saturating_add (1) ;"
      },
      {
        "id": 27,
        "label": "msg ! (\"Write path applied\") ;"
      },
      {
        "id": 28,
        "label": "r . power = r . power . saturating_add ((((s >> 4) & 0x7FFF) as u32) + 4) ;"
      },
      {
        "id": 29,
        "label": "a . rev = a . rev . saturating_add (1) ;"
      },
      {
        "id": 30,
        "label": "a . mask = a . mask . rotate_right (3) ^ ((s as u32) & 0xFFFF) ;"
      },
      {
        "id": 31,
        "label": "l . lines = l . lines . saturating_add (2) ;"
      },
      {
        "id": 32,
        "label": "msg ! (\"Non-write path applied\") ;"
      },
      {
        "id": 33,
        "label": "l . seed = l . seed . wrapping_add (s) ;"
      },
      {
        "id": 34,
        "label": "Ok (())"
      }
    ],
    "edges": [
      {
        "from": 14,
        "to": 14,
        "label": "def: a"
      },
      {
        "from": 15,
        "to": 15,
        "label": "def: e"
      },
      {
        "from": 16,
        "to": 16,
        "label": "def: r"
      },
      {
        "from": 17,
        "to": 17,
        "label": "def: l"
      },
      {
        "from": 18,
        "to": 18,
        "label": "def: s"
      },
      {
        "from": 14,
        "to": 18,
        "label": "data_dep: a"
      },
      {
        "from": 18,
        "to": 19,
        "label": "data_dep: s"
      },
      {
        "from": 18,
        "to": 19,
        "label": "data_dep: s"
      },
      {
        "from": 15,
        "to": 19,
        "label": "data_dep: e"
      },
      {
        "from": 15,
        "to": 19,
        "label": "data_dep: e"
      },
      {
        "from": 18,
        "to": 19,
        "label": "data_dep: s"
      },
      {
        "from": 18,
        "to": 20,
        "label": "data_dep: s"
      },
      {
        "from": 18,
        "to": 20,
        "label": "data_dep: s"
      },
      {
        "from": 15,
        "to": 21,
        "label": "data_dep: e"
      },
      {
        "from": 15,
        "to": 21,
        "label": "data_dep: e"
      },
      {
        "from": 18,
        "to": 21,
        "label": "data_dep: s"
      },
      {
        "from": 15,
        "to": 22,
        "label": "data_dep: e"
      },
      {
        "from": 15,
        "to": 22,
        "label": "data_dep: e"
      },
      {
        "from": 15,
        "to": 22,
        "label": "data_dep: e"
      },
      {
        "from": 18,
        "to": 22,
        "label": "data_dep: s"
      },
      {
        "from": 14,
        "to": 22,
        "label": "data_dep: a"
      },
      {
        "from": 14,
        "to": 22,
        "label": "data_dep: a"
      },
      {
        "from": 14,
        "to": 22,
        "label": "data_dep: a"
      },
      {
        "from": 14,
        "to": 22,
        "label": "data_dep: a"
      },
      {
        "from": 18,
        "to": 22,
        "label": "data_dep: s"
      },
      {
        "from": 17,
        "to": 22,
        "label": "data_dep: l"
      },
      {
        "from": 17,
        "to": 22,
        "label": "data_dep: l"
      },
      {
        "from": 16,
        "to": 22,
        "label": "data_dep: r"
      },
      {
        "from": 16,
        "to": 22,
        "label": "data_dep: r"
      },
      {
        "from": 18,
        "to": 22,
        "label": "data_dep: s"
      },
      {
        "from": 14,
        "to": 22,
        "label": "data_dep: a"
      },
      {
        "from": 14,
        "to": 22,
        "label": "data_dep: a"
      },
      {
        "from": 14,
        "to": 22,
        "label": "data_dep: a"
      },
      {
        "from": 14,
        "to": 22,
        "label": "data_dep: a"
      },
      {
        "from": 18,
        "to": 22,
        "label": "data_dep: s"
      },
      {
        "from": 17,
        "to": 22,
        "label": "data_dep: l"
      },
      {
        "from": 17,
        "to": 22,
        "label": "data_dep: l"
      },
      {
        "from": 15,
        "to": 23,
        "label": "data_dep: e"
      },
      {
        "from": 15,
        "to": 23,
        "label": "data_dep: e"
      },
      {
        "from": 18,
        "to": 23,
        "label": "data_dep: s"
      },
      {
        "from": 14,
        "to": 24,
        "label": "data_dep: a"
      },
      {
        "from": 14,
        "to": 24,
        "label": "data_dep: a"
      },
      {
        "from": 14,
        "to": 25,
        "label": "data_dep: a"
      },
      {
        "from": 14,
        "to": 25,
        "label": "data_dep: a"
      },
      {
        "from": 18,
        "to": 25,
        "label": "data_dep: s"
      },
      {
        "from": 17,
        "to": 26,
        "label": "data_dep: l"
      },
      {
        "from": 17,
        "to": 26,
        "label": "data_dep: l"
      },
      {
        "from": 16,
        "to": 28,
        "label": "data_dep: r"
      },
      {
        "from": 16,
        "to": 28,
        "label": "data_dep: r"
      },
      {
        "from": 18,
        "to": 28,
        "label": "data_dep: s"
      },
      {
        "from": 14,
        "to": 29,
        "label": "data_dep: a"
      },
      {
        "from": 14,
        "to": 29,
        "label": "data_dep: a"
      },
      {
        "from": 14,
        "to": 30,
        "label": "data_dep: a"
      },
      {
        "from": 14,
        "to": 30,
        "label": "data_dep: a"
      },
      {
        "from": 18,
        "to": 30,
        "label": "data_dep: s"
      },
      {
        "from": 17,
        "to": 31,
        "label": "data_dep: l"
      },
      {
        "from": 17,
        "to": 31,
        "label": "data_dep: l"
      },
      {
        "from": 17,
        "to": 33,
        "label": "data_dep: l"
      },
      {
        "from": 17,
        "to": 33,
        "label": "data_dep: l"
      },
      {
        "from": 18,
        "to": 33,
        "label": "data_dep: s"
      }
    ]
  }
]