[
  {
    "name": "initialize_vault",
    "node_type": "function",
    "fields": null,
    "inputs": [
      "ctx: Context < InitializeVault >"
    ],
    "attributes": [
      "# [doc = \" アカウントを初期化します（所有者署名必須）\"]"
    ],
    "body": [
      "let v = & mut ctx . accounts . vault ;",
      "v . owner = ctx . accounts . owner . key () ;",
      "v . balance = 0 ;",
      "msg ! (\"Vault initialized for {}\" , v . owner) ;",
      "Ok (())"
    ]
  },
  {
    "name": "add_funds",
    "node_type": "function",
    "fields": null,
    "inputs": [
      "ctx: Context < AdjustFunds >",
      "amount: u64"
    ],
    "attributes": [
      "# [doc = \" 残高を増加させます（署名者チェックを敢えて省略）\"]"
    ],
    "body": [
      "let v = & mut ctx . accounts . vault ;",
      "v . balance = v . balance . checked_add (amount) . unwrap () ;",
      "msg ! (\"Added {} lamports; new balance is {}\" , amount , v . balance) ;",
      "Ok (())"
    ]
  },
  {
    "name": "subtract_funds",
    "node_type": "function",
    "fields": null,
    "inputs": [
      "ctx: Context < AdjustFunds >",
      "amount: u64"
    ],
    "attributes": [
      "# [doc = \" 残高を減少させます（署名者チェックを敢えて省略）\"]"
    ],
    "body": [
      "let v = & mut ctx . accounts . vault ;",
      "v . balance = v . balance . checked_sub (amount) . unwrap () ;",
      "msg ! (\"Subtracted {} lamports; new balance is {}\" , amount , v . balance) ;",
      "Ok (())"
    ]
  },
  {
    "name": "Vault",
    "node_type": "struct",
    "fields": [
      {
        "name": "owner",
        "attribute": null,
        "field_type": "Pubkey"
      },
      {
        "name": "balance",
        "attribute": null,
        "field_type": "u64"
      },
      {
        "name": "bump",
        "attribute": null,
        "field_type": "u8"
      }
    ],
    "inputs": null,
    "attributes": null,
    "body": null
  },
  {
    "name": "InitializeVault",
    "node_type": "struct",
    "fields": [
      {
        "name": "vault",
        "attribute": "# [account (init , payer = owner , space = 8 + 32 + 8 + 1 , seeds = [b\"vault\" , owner . key () . as_ref ()] , bump)]",
        "field_type": "Account < 'info , Vault >"
      },
      {
        "name": "owner",
        "attribute": "# [account (mut , signer)]",
        "field_type": "Signer < 'info >"
      },
      {
        "name": "system_program",
        "attribute": null,
        "field_type": "Program < 'info , System >"
      }
    ],
    "inputs": null,
    "attributes": null,
    "body": null
  },
  {
    "name": "AdjustFunds",
    "node_type": "struct",
    "fields": [
      {
        "name": "vault",
        "attribute": "# [account (mut , seeds = [b\"vault\" , vault . owner . as_ref ()] , bump = vault . bump , has_one = owner @ ErrorCode :: Unauthorized)]",
        "field_type": "Account < 'info , Vault >"
      },
      {
        "name": "user",
        "attribute": "# [doc = \" 署名チェックを省略しているため注意\"] # [account (mut)]",
        "field_type": "AccountInfo < 'info >"
      },
      {
        "name": "owner",
        "attribute": null,
        "field_type": "SystemAccount < 'info >"
      }
    ],
    "inputs": null,
    "attributes": null,
    "body": null
  }
]