[
  {
    "name": "update",
    "inputs": [
      "ctx: Context < Update >",
      "delta: u8"
    ],
    "nodes": [
      {
        "id": 0,
        "label": "Entry"
      },
      {
        "id": 1,
        "label": "let buf = & mut ctx . accounts . meta . try_borrow_mut_data () ? ;"
      },
      {
        "id": 2,
        "label": "if delta & 0x1 == 1 { buf [0] = ! buf [0] ; } else { buf [0] = buf [0] . wrapping_add (delta) ; }"
      },
      {
        "id": 3,
        "label": "buf [0] = ! buf [0] ;"
      },
      {
        "id": 4,
        "label": "buf [0] = buf [0] . wrapping_add (delta) ;"
      },
      {
        "id": 5,
        "label": "msg ! (\"更新者 {} による update 実行\" , ctx . accounts . updater . key ()) ;"
      },
      {
        "id": 6,
        "label": "Ok (())"
      }
    ],
    "edges": [
      {
        "from": 1,
        "to": 1,
        "label": "def: buf"
      },
      {
        "from": 1,
        "to": 2,
        "label": "data_dep: buf"
      },
      {
        "from": 1,
        "to": 2,
        "label": "data_dep: buf"
      },
      {
        "from": 1,
        "to": 2,
        "label": "data_dep: buf"
      },
      {
        "from": 1,
        "to": 2,
        "label": "data_dep: buf"
      },
      {
        "from": 1,
        "to": 3,
        "label": "data_dep: buf"
      },
      {
        "from": 1,
        "to": 3,
        "label": "data_dep: buf"
      },
      {
        "from": 1,
        "to": 4,
        "label": "data_dep: buf"
      },
      {
        "from": 1,
        "to": 4,
        "label": "data_dep: buf"
      }
    ]
  }
]