[
  {
    "name": "set_reminder",
    "node_type": "function",
    "fields": null,
    "inputs": [
      "ctx: Context < SetReminder >",
      "at: i64"
    ],
    "attributes": [],
    "body": [
      "let now = Clock :: get () ? . unix_timestamp ;",
      "let r = & mut ctx . accounts . reminder ;",
      "r . when = at ;",
      "r . active = true ;",
      "r . created_at = now ;",
      "Ok (())"
    ]
  },
  {
    "name": "stop_reminder",
    "node_type": "function",
    "fields": null,
    "inputs": [
      "ctx: Context < StopReminder >"
    ],
    "attributes": [],
    "body": [
      "let now = Clock :: get () ? . unix_timestamp ;",
      "let r = & mut ctx . accounts . reminder ;",
      "r . active = false ;",
      "r . stopped_at = now ;",
      "Ok (())"
    ]
  },
  {
    "name": "SetReminder",
    "node_type": "struct",
    "fields": [
      {
        "name": "reminder",
        "attribute": "# [account (init , payer = user , space = 8 + 8 * 3 + 1)]",
        "field_type": "Account < 'info , ReminderData >"
      },
      {
        "name": "user",
        "attribute": "# [account (mut)]",
        "field_type": "Signer < 'info >"
      },
      {
        "name": "system_program",
        "attribute": null,
        "field_type": "Program < 'info , System >"
      }
    ],
    "inputs": null,
    "attributes": null,
    "body": null
  },
  {
    "name": "StopReminder",
    "node_type": "struct",
    "fields": [
      {
        "name": "reminder",
        "attribute": null,
        "field_type": "Account < 'info , ReminderData >"
      },
      {
        "name": "user",
        "attribute": "# [account (mut)]",
        "field_type": "Signer < 'info >"
      },
      {
        "name": "system_program",
        "attribute": null,
        "field_type": "Program < 'info , System >"
      }
    ],
    "inputs": null,
    "attributes": null,
    "body": null
  },
  {
    "name": "ReminderData",
    "node_type": "struct",
    "fields": [
      {
        "name": "when",
        "attribute": null,
        "field_type": "i64"
      },
      {
        "name": "active",
        "attribute": null,
        "field_type": "bool"
      },
      {
        "name": "created_at",
        "attribute": null,
        "field_type": "i64"
      },
      {
        "name": "stopped_at",
        "attribute": null,
        "field_type": "i64"
      }
    ],
    "inputs": null,
    "attributes": null,
    "body": null
  }
]